impactchart/__init__.py
impactchart/backend/__init__.py
impactchart/backend/base.py
impactchart/backend/bokeh_backend.py
impactchart/backend/matplotlib.py
impactchart/cli/__init__.py
impactchart/cli/main.py
impactchart/model.py
impactchart-0.6.0.dist-info/LICENSE.md
impactchart-0.6.0.dist-info/METADATA
impactchart-0.6.0.dist-info/WHEEL
impactchart-0.6.0.dist-info/entry_points.txt
impactchart-0.6.0.dist-info/RECORD
