Metadata-Version: 2.1
Name: impactchart
Version: 0.6.0
Summary: A package for generating impact charts.
Home-page: https://github.com/vengroff/impactchart
License: HL3-CL-ECO-EXTR-FFD-LAW-MIL-SV
Keywords: impact charts,regression,machine learning,analysis
Author: Darren Vengroff
Requires-Python: >=3.11,<4.0
Classifier: Development Status :: 3 - Alpha
Classifier: Intended Audience :: Science/Research
Classifier: License :: Other/Proprietary License
Classifier: Operating System :: MacOS :: MacOS X
Classifier: Operating System :: Microsoft :: Windows
Classifier: Operating System :: POSIX :: Linux
Classifier: Programming Language :: Python :: 3
Classifier: Programming Language :: Python :: 3.11
Classifier: Programming Language :: Python :: 3.12
Provides-Extra: bokeh
Provides-Extra: jupyterlab
Requires-Dist: PyYAML (>=6.0,<7.0)
Requires-Dist: bokeh (>=3.5.0,<4.0.0) ; extra == "bokeh"
Requires-Dist: deprecated (>=1.2.14,<2.0.0)
Requires-Dist: ipywidgets (>=8.1.3,<9.0.0) ; extra == "jupyterlab"
Requires-Dist: jupyterlab (>=4.2.3,<5.0.0) ; extra == "jupyterlab"
Requires-Dist: logargparser (>=0.1.1,<0.2.0)
Requires-Dist: matplotlib (>=3.9.1,<4.0.0)
Requires-Dist: shap (>=0.46.0,<0.47.0)
Requires-Dist: usingversion (>=0.1.1,<0.2.0)
Requires-Dist: xgboost (>=2.1.0,<3.0.0)
Project-URL: Repository, https://github.com/vengroff/impactchart
